<?xml version="1.0" encoding="utf-8"?>
<layer-list
  xmlns:android="http://schemas.android.com/apk/res/android">
    <item android:id="@*android:id/background">
        <shape>
            <solid android:color="@*android:color/background_dark" />
        </shape>
    </item>
    <item android:id="@*android:id/progress">
        <scale android:scaleWidth="100%">
            <shape>
                <corners android:topLeftRadius="0.0dip" android:topRightRadius="8.0dip" android:bottomLeftRadius="0.0dip" android:bottomRightRadius="8.0dip" />
                <gradient android:startColor="#00ff00" android:endColor="#ff00ff" android:angle="45.0" android:centerColor="#fff000" />
            </shape>
        </scale>
    </item>
</layer-list>