<?xml version="1.0" encoding="utf-8"?>
<vector android:height="56.0dip" android:width="56.0dip" android:autoMirrored="true" android:viewportWidth="48.0" android:viewportHeight="48.0"
  xmlns:android="http://schemas.android.com/apk/res/android">
    <path android:fillColor="@*android:color/ripple_material_dark" android:pathData="M24,48C37.2548,48 48,37.2548 48,24C48,10.7452 37.2548,0 24,0C10.7452,0 0,10.7452 0,24C0,37.2548 10.7452,48 24,48Z" />
    <path android:fillColor="@*android:color/background_dark" android:pathData="M47.9973,24C47.9373,34.4673 41.1054,43.3364 31.6364,46.4945C29.2364,47.2936 26.67,47.7273 24,47.7273C10.7918,47.73 0.0736,37.1182 0,24C0,24.0464 0,24.09 0,24.1364C0,37.3145 10.7455,48 24,48C26.67,48 29.2364,47.5664 31.6364,46.7673C41.1464,43.5954 48,34.6609 48,24.1364C48,24.09 47.9973,24.0464 47.9973,24Z" android:strokeAlpha="0.1" android:fillAlpha="0.1" />
    <path android:fillColor="@*android:color/ripple_material_dark" android:pathData="M48,24C48,13.4155 41.1464,4.4318 31.6364,1.2409C29.2364,0.4364 26.67,0 24,0C10.7455,0 0,10.7455 0,24" android:strokeAlpha="0.4" android:fillAlpha="0.4" />
    <path android:fillColor="#4285f4" android:pathData="M27.6871,22.6991L32.8961,18.7309L35.2089,13.74C33.668,10.8 31.0089,8.5391 27.8152,7.5355L23.0071,10.7809L20.2798,16.4918C21.1661,15.42 22.4971,14.7436 23.9889,14.7436C26.6725,14.7436 28.8161,16.9118 28.8161,19.5709C28.8161,20.7627 28.388,21.8591 27.6871,22.6991Z" />
    <path android:fillColor="#4285f4" android:pathData="M23.9889,6.9546C20.0944,6.9546 16.6417,8.7028 14.3071,11.4791L16.5271,15.1173L20.2771,16.4946C20.3017,16.47 27.8126,7.5382 27.8126,7.5382C26.6017,7.1646 25.3171,6.9546 23.9889,6.9546Z" />
    <path android:fillColor="#fbbc05" android:pathData="M27.6871,22.6991C26.8007,23.7491 25.4807,24.4255 23.9889,24.4255C21.3053,24.4255 19.1616,22.2573 19.1616,19.5982C19.1616,18.4555 19.628,17.3127 20.2825,16.4946L14.7434,20.4546L12.6025,25.6391C13.9334,28.5327 16.1262,30.8645 18.3871,33.78L24.3189,29.0591L27.6871,22.6991Z" />
    <path android:fillColor="#34a853" android:pathData="M36.6547,19.5982C36.6547,17.4764 36.1174,15.4937 35.2092,13.7428L18.3901,33.78C19.1374,34.7373 19.8601,35.7628 20.5829,36.8837C23.1492,40.8491 22.3801,43.2273 24.011,43.2273C25.6665,43.2273 24.9438,40.8491 27.5101,36.8837C31.732,30.2809 36.6547,27.2728 36.6547,19.5982Z" />
    <path android:fillColor="#ea4335" android:pathData="M20.28,16.4945L14.3073,11.4791C12.4664,13.6718 11.3455,16.5191 11.3455,19.5982C11.3455,21.9763 11.8118,23.9127 12.6055,25.6391L20.28,16.4945Z" />
</vector>